{
  "contacts": [
    {
      "id": "wk6zFDSwnjZQcfyasMg7x",
      "name": "Felix Ondullah",
      "email": "felixondullah@gmail.com"
    },
    {
      "id": "cQ0iz80lrBaXDOPjQtYq9",
      "name": "Felix Ondullah",
      "email": "felixondullah@gmail.com",
      "number": "0714225569"
    },
    {
      "id": "ifj2w9ZzMPTz0i8UHHijw",
      "name": "Felix Ondullah",
      "email": "felixondullah@gmail.com",
      "number": "0714225569"
    },
    {
      "id": "HxadDyFlD9iYGoIfLYMqo",
      "name": "Felix",
      "email": "felixondullah@gmail.com",
      "number": "0714225569"
    },
    {
      "id": "hUYpPY-rLIPl3qAhVnxxt",
      "name": "Felix",
      "email": "felixondullah@gmail.com",
      "number": "0714225569"
    },
    {
      "id": "MEqKjNzEnbUQus8U-YQBD",
      "name": "Felix",
      "email": "felixondullah@gmail.com",
      "number": "0714225569"
    }
  ]
}